llama_index/tools/azure_translate/__init__.py
llama_index/tools/azure_translate/base.py
llama_index_tools_azure_translate-0.4.1.dist-info/METADATA
llama_index_tools_azure_translate-0.4.1.dist-info/WHEEL
llama_index_tools_azure_translate-0.4.1.dist-info/licenses/LICENSE
llama_index_tools_azure_translate-0.4.1.dist-info/RECORD
